pollination_handlers/__init__.py
pollination_handlers/inputs/__init__.py
pollination_handlers/inputs/bool_options.py
pollination_handlers/inputs/data.py
pollination_handlers/inputs/ddy.py
pollination_handlers/inputs/emissions.py
pollination_handlers/inputs/helper.py
pollination_handlers/inputs/model.py
pollination_handlers/inputs/north.py
pollination_handlers/inputs/pit.py
pollination_handlers/inputs/postprocess.py
pollination_handlers/inputs/radiancepar.py
pollination_handlers/inputs/runperiod.py
pollination_handlers/inputs/schedule.py
pollination_handlers/inputs/simulation.py
pollination_handlers/inputs/wea.py
pollination_handlers/outputs/__init__.py
pollination_handlers/outputs/comfort.py
pollination_handlers/outputs/daylight.py
pollination_handlers/outputs/eui.py
pollination_handlers/outputs/helper.py
pollination_handlers/outputs/summary.py
pollination_handlers-0.10.12.dist-info/LICENSE
pollination_handlers-0.10.12.dist-info/METADATA
pollination_handlers-0.10.12.dist-info/WHEEL
pollination_handlers-0.10.12.dist-info/top_level.txt
pollination_handlers-0.10.12.dist-info/RECORD
