Metadata-Version: 2.1
Name: pollination-handlers
Version: 0.10.12
Summary: Handlers to process Pollination recipes inputs and outputs.
Home-page: https://github.com/pollination/handlers-python
Author: Pollination
Author-email: info@ladybug.tools
License: AGPL-3.0
Classifier: Programming Language :: Python :: 2.7
Classifier: Programming Language :: Python :: 3.6
Classifier: Programming Language :: Python :: 3.7
Classifier: Programming Language :: Python :: Implementation :: CPython
Classifier: License :: OSI Approved :: GNU Affero General Public License v3
Classifier: Operating System :: OS Independent
License-File: LICENSE
Requires-Dist: lbt-dragonfly>=0.11.682
